manyq/__init__.py
manyq/manyq.py
manyq-0.0.1.dist-info/LICENSE
manyq-0.0.1.dist-info/METADATA
manyq-0.0.1.dist-info/WHEEL
manyq-0.0.1.dist-info/top_level.txt
manyq-0.0.1.dist-info/RECORD
