Metadata-Version: 2.1
Name: manyq
Version: 0.0.1
Summary: Fast quantum computer simulator for Quantum Machine Learning
Home-page: https://github.com/entropicalabs/manyQ
Author: Joaquin Keller
Author-email: joaquin@entropicalabs.io
License: Apache 2.0
Keywords: qubit,quantum
Platform: UNKNOWN
Classifier: Development Status :: 4 - Beta
Classifier: License :: OSI Approved :: Apache Software License
Classifier: Programming Language :: Python :: 3
